<?xml version="1.0"?>
<registry>

  <records prefix="plone.resources/barceloneta"
            interface='Products.CMFPlone.interfaces.IResourceRegistry'>
      <value key="css">
        <element>++plone++barceloneta/less/barceloneta.plone.less</element>
      </value>
  </records>

  <record name="plone.lessvariables">
    <field type="plone.registry.field.Dict">
      <title>Less variables</title>
      <description>Variables that are going to be compiled on less</description>
      <key_type type="plone.registry.field.ASCIILine" />
      <value_type type="plone.registry.field.TextLine" />
    </field>
    <value purge="false">
      <element key="plone-body-bg">#fafafa</element>
    </value>
  </record>

  <records interface="Products.CMFPlone.interfaces.ITinyMCESchema"
           prefix="plone">
    <value key="content_css" purge="false">++plone++barceloneta/less/barceloneta-compiled.css</value>
  </records>

  <records prefix="plone.bundles/barceloneta"
            interface='Products.CMFPlone.interfaces.IBundleRegistry'>
    <value key="resources">
      <element>barceloneta</element>
    </value>
    <value key="csscompilation">++plone++barceloneta/less/barceloneta-compiled.css</value>
    <value key="last_compilation">2014-08-14 00:00:00</value>
    <value key="enabled">True</value>
    <value key="depends">plone</value>
  </records>
</registry>
